_pyrsistent_version.py
pvectorc.cp38-win32.pyd
pyrsistent/__init__.py
pyrsistent/__init__.pyi
pyrsistent/_checked_types.py
pyrsistent/_field_common.py
pyrsistent/_helpers.py
pyrsistent/_immutable.py
pyrsistent/_pbag.py
pyrsistent/_pclass.py
pyrsistent/_pdeque.py
pyrsistent/_plist.py
pyrsistent/_pmap.py
pyrsistent/_precord.py
pyrsistent/_pset.py
pyrsistent/_pvector.py
pyrsistent/_toolz.py
pyrsistent/_transformations.py
pyrsistent/py.typed
pyrsistent/typing.py
pyrsistent/typing.pyi
pyrsistent-0.17.4rc1.dist-info/LICENSE.mit
pyrsistent-0.17.4rc1.dist-info/METADATA
pyrsistent-0.17.4rc1.dist-info/WHEEL
pyrsistent-0.17.4rc1.dist-info/top_level.txt
pyrsistent-0.17.4rc1.dist-info/RECORD
