Metadata-Version: 2.1
Name: pyrsistent
Version: 0.17.4rc1
Summary: Persistent/Functional/Immutable data structures
Home-page: http://github.com/tobgu/pyrsistent/
Author: Tobias Gustafsson
Author-email: tobias.l.gustafsson@gmail.com
License: MIT
Platform: UNKNOWN
Classifier: Intended Audience :: Developers
Classifier: License :: OSI Approved :: MIT License
Classifier: Operating System :: OS Independent
Classifier: Programming Language :: Python :: 3.6
Classifier: Programming Language :: Python :: 3.7
Classifier: Programming Language :: Python :: 3.8
Classifier: Programming Language :: Python :: 3.9
Classifier: Programming Language :: Python :: Implementation :: PyPy
Requires-Python: >=3.6
License-File: LICENSE.mit
